odoo/addons/pos_session_closing_stock_error/README.rst
odoo/addons/pos_session_closing_stock_error/__init__.py
odoo/addons/pos_session_closing_stock_error/__manifest__.py
odoo/addons/pos_session_closing_stock_error/i18n/pos_session_closing_stock_error.pot
odoo/addons/pos_session_closing_stock_error/models/__init__.py
odoo/addons/pos_session_closing_stock_error/models/pos_config.py
odoo/addons/pos_session_closing_stock_error/models/pos_session.py
odoo/addons/pos_session_closing_stock_error/readme/CONFIGURE.rst
odoo/addons/pos_session_closing_stock_error/readme/CONTRIBUTORS.rst
odoo/addons/pos_session_closing_stock_error/readme/DESCRIPTION.rst
odoo/addons/pos_session_closing_stock_error/static/description/error_msg.png
odoo/addons/pos_session_closing_stock_error/static/description/icon.png
odoo/addons/pos_session_closing_stock_error/static/description/index.html
odoo/addons/pos_session_closing_stock_error/static/description/session_with_errors.png
odoo/addons/pos_session_closing_stock_error/tests/__init__.py
odoo/addons/pos_session_closing_stock_error/tests/test_pos.py
odoo/addons/pos_session_closing_stock_error/views/pos_config_views.xml
odoo12_addon_pos_session_closing_stock_error-12.0.1.0.1.dist-info/METADATA
odoo12_addon_pos_session_closing_stock_error-12.0.1.0.1.dist-info/WHEEL
odoo12_addon_pos_session_closing_stock_error-12.0.1.0.1.dist-info/top_level.txt
odoo12_addon_pos_session_closing_stock_error-12.0.1.0.1.dist-info/RECORD
